itaxotools/__pyinstaller/hook-itaxotools.taxi_gui.py
itaxotools/taxi_gui/__init__.py
itaxotools/taxi_gui/config.py
itaxotools/taxi_gui/io.py
itaxotools/taxi_gui/loop.py
itaxotools/taxi_gui/resources.py
itaxotools/taxi_gui/threading.py
itaxotools/taxi_gui/utility.py
itaxotools/taxi_gui/app/__init__.py
itaxotools/taxi_gui/app/application.py
itaxotools/taxi_gui/app/config.py
itaxotools/taxi_gui/app/model.py
itaxotools/taxi_gui/app/resources.py
itaxotools/taxi_gui/app/skin.py
itaxotools/taxi_gui/app/tasks.py
itaxotools/taxi_gui/logos/taxi2.ico
itaxotools/taxi_gui/logos/taxi2.svg
itaxotools/taxi_gui/logos/taxi3.ico
itaxotools/taxi_gui/logos/taxi3.svg
itaxotools/taxi_gui/main/__init__.py
itaxotools/taxi_gui/main/body.py
itaxotools/taxi_gui/main/dashboard.py
itaxotools/taxi_gui/main/footer.py
itaxotools/taxi_gui/main/header.py
itaxotools/taxi_gui/main/main.py
itaxotools/taxi_gui/main/sidebar.py
itaxotools/taxi_gui/model/__init__.py
itaxotools/taxi_gui/model/common.py
itaxotools/taxi_gui/model/input_file.py
itaxotools/taxi_gui/model/partition.py
itaxotools/taxi_gui/model/sequence.py
itaxotools/taxi_gui/model/tasks.py
itaxotools/taxi_gui/model/tree.py
itaxotools/taxi_gui/tasks/common/model.py
itaxotools/taxi_gui/tasks/common/process.py
itaxotools/taxi_gui/tasks/common/types.py
itaxotools/taxi_gui/tasks/common/view.py
itaxotools/taxi_gui/tasks/decontaminate/__init__.py
itaxotools/taxi_gui/tasks/decontaminate/model.py
itaxotools/taxi_gui/tasks/decontaminate/process.py
itaxotools/taxi_gui/tasks/decontaminate/types.py
itaxotools/taxi_gui/tasks/decontaminate/view.py
itaxotools/taxi_gui/tasks/dereplicate/__init__.py
itaxotools/taxi_gui/tasks/dereplicate/model.py
itaxotools/taxi_gui/tasks/dereplicate/process.py
itaxotools/taxi_gui/tasks/dereplicate/view.py
itaxotools/taxi_gui/tasks/versus_all/__init__.py
itaxotools/taxi_gui/tasks/versus_all/model.py
itaxotools/taxi_gui/tasks/versus_all/process.py
itaxotools/taxi_gui/tasks/versus_all/types.py
itaxotools_taxi_gui-0.2.5.dist-info/licenses/LICENSE.txt
itaxotools_taxi_gui-0.2.5.dist-info/METADATA
itaxotools_taxi_gui-0.2.5.dist-info/WHEEL
itaxotools_taxi_gui-0.2.5.dist-info/entry_points.txt
itaxotools_taxi_gui-0.2.5.dist-info/top_level.txt
itaxotools_taxi_gui-0.2.5.dist-info/RECORD
